{
  "cloud": [
    { "id": 1, "CPU_UTILIZATION": 86, "MEMORY_UTILIZATION": 76,"DISK_UTILIZATION": 61 },
    { "id": 2, "CPU_UTILIZATION": 85, "MEMORY_UTILIZATION": 76,"DISK_UTILIZATION": 61 },
    { "id": 3, "CPU_UTILIZATION": 86, "MEMORY_UTILIZATION": 75,"DISK_UTILIZATION": 61 },
    { "id": 4, "CPU_UTILIZATION": 86, "MEMORY_UTILIZATION": 76,"DISK_UTILIZATION": 60 },
    { "id": 5, "CPU_UTILIZATION": 80, "MEMORY_UTILIZATION": 70,"DISK_UTILIZATION": 65 },
	{ "id": 6, "CPU_UTILIZATION": 85, "MEMORY_UTILIZATION": 75,"DISK_UTILIZATION": 60 },
    { "id": 7, "CPU_UTILIZATION": 45, "MEMORY_UTILIZATION": 23,"DISK_UTILIZATION": 16}
  ],
  "output":[
      { "id": 1, "alert": "No Alert, 1"}
  ]
}